{
	"style": "flat",
	"description": "Remote control for Rasberry-based robot",
	"pagebuttonwidth": "static",
	"type": "NetIOConfiguration",
	"preventSleep": true,
	"name": "RoboBerry Node",
	"connections": [
		{
			"name": "connection",
			"host": "192.168.1.145",
			"port": 54321,
			"protocol": "http"
		}
	],
	"theme": "dark",
	"version": 2,
	"device": "Galaxy Tab 10 1",
	"navigation": "fixed",
	"pages": [
		{
			"name": "Main",
			"items": [
				{
					"text": "Robot Control V3.2",
					"top": 0,
					"height": 40,
					"width": 270,
					"fontsize": 25,
					"type": "label",
					"textalign": "left",
					"left": 20
				},
				{
					"text": "http://paolonegrini.wordpress.com/",
					"top": 30,
					"height": 30,
					"width": 420,
					"textcolor": "150,150,150",
					"type": "label",
					"textalign": "left",
					"left": 20,
					"fontsize": 14
				},
				{
					"requiresSendReponse": false,
					"sends": [
						"/SHUTDOWN"
					],
					"top": 590,
					"shape": "rounded",
					"height": 50,
					"width": 90,
					"connection": "connection",
					"background": "190,0,0",
					"left": 1170,
					"type": "button",
					"icon": "standby"
				},
				{
					"text": "Info",
					"top": 460,
					"interval": 500,
					"height": 260,
					"width": 260,
					"reads": "/READ?Read_Info",
					"background": "189,185,185",
					"parseResponse": "\\S( .*)",
					"type": "label",
					"formatResponse": "{0}",
					"left": 640
				},
				{
					"text": "Motors",
					"top": 80,
					"height": 40,
					"width": 110,
					"type": "label",
					"left": 20
				},
				{
					"text": "Arduino debug",
					"top": 320,
					"height": 40,
					"width": 110,
					"type": "label",
					"left": 20
				},
				{
					"text": "Auto mode",
					"top": 140,
					"height": 40,
					"width": 110,
					"type": "label",
					"left": 20
				},
				{
					"text": "Log",
					"top": 200,
					"height": 40,
					"width": 110,
					"type": "label",
					"left": 20
				},
				{
					"offSend": "/SCMD?Motors=0",
					"top": 80,
					"height": 40,
					"offColor": "255,0,0",
					"width": 150,
					"onSend": "/SCMD?Motors=1",
					"type": "switch",
					"left": 140
				},
				{
					"offSend": "/SCMD?SerialDebug=0",
					"top": 320,
					"offText": "Off",
					"height": 40,
					"width": 150,
					"onText": "On",
					"onSend": "/SCMD?SerialDebug=1",
					"type": "switch",
					"left": 140
				},
				{
					"offSend": "/SCMD?AutoNav=0",
					"requiresSendReponse": false,
					"top": 140,
					"offText": "Off",
					"height": 40,
					"width": 150,
					"onValue": "CH03_ON",
					"onText": "On",
					"onSend": "/SCMD?AutoNav=1",
					"type": "switch",
					"left": 140
				},
				{
					"offSend": "/LOG_OFF",
					"requiresSendReponse": true,
					"top": 200,
					"onSend": "/LOG_ON",
					"width": 150,
					"height": 40,
					"type": "switch",
					"left": 140
				},
				{
					"icon": "next",
					"requiresSendReponse": false,
					"sends": [
						"/REBOOT=1"
					],
					"top": 470,
					"shape": "rounded",
					"height": 50,
					"width": 90,
					"connection": "connection",
					"background": "0,76,190",
					"type": "button",
					"left": 1040
				},
				{
					"sends": [
						"/SCMD?E_EEPROM=1 1"
					],
					"top": 470,
					"label": "Erase EEPROM",
					"width": 90,
					"shape": "rounded",
					"background": "190,0,0",
					"height": 50,
					"type": "button",
					"left": 910
				},
				{
					"sends": [
						"/SCMD?SaveCfg=1"
					],
					"top": 530,
					"label": "Save config",
					"width": 90,
					"shape": "rounded",
					"height": 50,
					"type": "button",
					"left": 910
				},
				{
					"sends": [
						"/SCMD?Load_def=1"
					],
					"top": 590,
					"label": "Load defaults",
					"width": 90,
					"shape": "rounded",
					"height": 50,
					"type": "button",
					"left": 910
				},
				{
					"sends": "/SCMD?APIDConKp_{value}",
					"parseResponse": "\\d+",
					"top": 80,
					"maxValue": 1500,
					"reads": "/READ?Read_APIDKp",
					"minValue": 0,
					"height": 370,
					"width": 40,
					"showValue": true,
					"type": "slider",
					"formatResponse": "{0}",
					"left": 360,
					"step": 1
				},
				{
					"sends": "/SCMD?APIDConKi_{value}",
					"parseResponse": "\\d+",
					"top": 80,
					"maxValue": 2000,
					"reads": "/READ?Read_APIDKi",
					"minValue": 0,
					"height": 370,
					"width": 40,
					"step": 1,
					"showValue": true,
					"type": "slider",
					"formatResponse": "{0}",
					"left": 420
				},
				{
					"text": "Kp",
					"top": 40,
					"height": 30,
					"width": 60,
					"type": "label",
					"left": 350
				},
				{
					"text": "Ki",
					"top": 40,
					"height": 30,
					"width": 60,
					"type": "label",
					"left": 410
				},
				{
					"sends": "/SCMD?APIDConKd_{value}",
					"parseResponse": "\\d+",
					"top": 80,
					"maxValue": 200,
					"reads": "/READ?Read_APIDKd",
					"minValue": 0,
					"height": 370,
					"width": 40,
					"step": 1,
					"showValue": true,
					"type": "slider",
					"formatResponse": "{0}",
					"left": 480
				},
				{
					"text": "Kd",
					"top": 40,
					"height": 30,
					"width": 60,
					"type": "label",
					"left": 470
				},
				{
					"text": "Angle PID",
					"top": 10,
					"height": 40,
					"width": 160,
					"type": "label",
					"left": 360
				},
				{
					"sends": "/SCMD?SPIDKp_{value}",
					"parseResponse": "\\d+",
					"top": 80,
					"maxValue": 7000,
					"reads": "/READ?Read_SPIDKp",
					"minValue": 2000,
					"height": 370,
					"width": 40,
					"step": 1,
					"showValue": true,
					"type": "slider",
					"formatResponse": "{0}",
					"left": 720
				},
				{
					"sends": "/SCMD?SPIDKi_{value}",
					"parseResponse": "\\d+",
					"top": 80,
					"maxValue": 300,
					"reads": "/READ?Read_SPIDKi",
					"minValue": 0,
					"height": 370,
					"width": 40,
					"step": 1,
					"showValue": true,
					"type": "slider",
					"formatResponse": "{0}",
					"left": 780
				},
				{
					"sends": "/SCMD?SPIDKd_{value}",
					"parseResponse": "\\d+",
					"top": 80,
					"maxValue": 150,
					"reads": "/READ?Read_SPIDKd",
					"minValue": 0,
					"height": 370,
					"width": 40,
					"step": 1,
					"showValue": true,
					"type": "slider",
					"formatResponse": "{0}",
					"left": 840
				},
				{
					"text": "Kp",
					"top": 40,
					"height": 30,
					"width": 60,
					"type": "label",
					"left": 710
				},
				{
					"text": "Ki",
					"top": 40,
					"height": 30,
					"width": 60,
					"type": "label",
					"left": 770
				},
				{
					"text": "Kd",
					"top": 40,
					"height": 30,
					"width": 60,
					"type": "label",
					"left": 830
				},
				{
					"text": "Speed PID",
					"top": 10,
					"height": 40,
					"width": 160,
					"type": "label",
					"left": 720
				},
				{
					"text": "pitch",
					"top": 370,
					"interval": 300,
					"height": 40,
					"width": 80,
					"reads": "/READ?Read_Pitch",
					"parseResponse": "([-0-9]+\\.[0-9]+)",
					"type": "label",
					"textalign": "left",
					"formatResponse": "P: {0}",
					"left": 40
				},
				{
					"text": "yaw",
					"top": 370,
					"interval": 320,
					"height": 40,
					"width": 80,
					"reads": "/READ?Read_Yaw",
					"parseResponse": "([-0-9]+\\.[0-9]+)",
					"type": "label",
					"textalign": "left",
					"formatResponse": "Y: {0}",
					"left": 140
				},
				{
					"text": "roll",
					"top": 370,
					"interval": 350,
					"height": 40,
					"width": 60,
					"reads": "/READ?Read_Roll",
					"parseResponse": "([-0-9]+\\.[0-9]+)",
					"type": "label",
					"textalign": "left",
					"formatResponse": "R: {0}",
					"left": 230
				},
				{
					"text": "LT",
					"top": 410,
					"interval": 2000,
					"height": 40,
					"width": 70,
					"reads": "/READ?Read_LoopT",
					"parseResponse": "\\d+",
					"textcolor": "230,230,230",
					"type": "label",
					"formatResponse": "CALC(1/({0}/1000);0) Hz",
					"left": 10
				},
				{
					"text": "CPU Temp",
					"top": 410,
					"height": 40,
					"width": 80,
					"reads": "/READ?Read_CPUT",
					"parseResponse": "\\d+",
					"type": "label",
					"textalign": "left",
					"formatResponse": "CPU: {0}.{1} C",
					"left": 140
				},
				{
					"text": "ISTE",
					"top": 410,
					"height": 40,
					"width": 80,
					"reads": "/READ?Read_ISTE",
					"parseResponse": "\\d+",
					"type": "label",
					"textalign": "left",
					"formatResponse": "E: {0}.{1}",
					"left": 230,
					"interval": 300
				},
				{
					"comment": "Angle Kp",
					"sends": "/SCMD?APIDAggKp_{value}",
					"parseResponse": "\\d+",
					"top": 80,
					"maxValue": 5000,
					"reads": "/READ?Read_APIDAggKp",
					"minValue": 0,
					"height": 370,
					"width": 40,
					"step": 1,
					"showValue": true,
					"type": "slider",
					"formatResponse": "{0}",
					"left": 540
				},
				{
					"sends": "/SCMD?APIDAggKi_{value}",
					"parseResponse": "\\d+",
					"top": 80,
					"maxValue": 5000,
					"reads": "/READ?Read_APIDAggKi",
					"minValue": 0,
					"height": 370,
					"width": 40,
					"step": 1,
					"showValue": true,
					"type": "slider",
					"formatResponse": "{0}",
					"left": 600
				},
				{
					"sends": "/SCMD?APIDAgKd_{value}",
					"parseResponse": "\\d+",
					"top": 80,
					"maxValue": 1500,
					"reads": "/READ?Read_APIDAggKd",
					"minValue": 0,
					"height": 370,
					"width": 40,
					"step": 1,
					"showValue": true,
					"type": "slider",
					"formatResponse": "{0}",
					"left": 660
				},
				{
					"text": "Kd",
					"top": 40,
					"height": 30,
					"width": 60,
					"type": "label",
					"left": 650
				},
				{
					"text": "Ki",
					"top": 40,
					"height": 30,
					"width": 60,
					"type": "label",
					"left": 590
				},
				{
					"text": "Kp",
					"top": 40,
					"height": 30,
					"width": 60,
					"type": "label",
					"left": 530
				},
				{
					"text": "Angle PID AGG",
					"top": 10,
					"height": 40,
					"width": 160,
					"type": "label",
					"left": 540
				},
				{
					"sends": "/SCMD?calibratedZeroAngle_{value}",
					"parseResponse": "\\d+",
					"top": 80,
					"maxValue": 400,
					"reads": "/READ?Read_calibratedZeroAngle",
					"minValue": -200,
					"height": 370,
					"width": 40,
					"connection": "connection",
					"step": 1,
					"showValue": true,
					"type": "slider",
					"formatResponse": "{0}",
					"left": 300,
					"reset": 180
				},
				{
					"reloadButton": true,
					"url": "http://192.168.1.145:9000/javascript_simple.html",
					"top": 470,
					"height": 240,
					"width": 320,
					"type": "webview",
					"left": 20,
					"scrollable": false
				},
				{
					"reset": 0,
					"showValue": false,
					"sends": "/SCMD?Throttle_{value}",
					"knobColor": "55,55,55",
					"top": 80,
					"maxValue": 30,
					"minValue": -30,
					"width": 40,
					"textcolor": "230,230,230",
					"highColor": "65,65,65",
					"release": "/SCMD?Throttle_0",
					"height": 300,
					"type": "slider",
					"lowColor": "45,45,45",
					"left": 910
				},
				{
					"reset": 0,
					"showValue": false,
					"sends": "/SCMD?Steer_{value}",
					"knobColor": "55,55,55",
					"top": 390,
					"maxValue": 20,
					"minValue": -20,
					"width": 300,
					"textcolor": "230,230,230",
					"highColor": "65,65,65",
					"release": "/SCMD?Steer_0",
					"height": 40,
					"type": "slider",
					"lowColor": "45,45,45",
					"left": 960
				},
				{
					"requiresSendReponse": false,
					"top": 530,
					"connection": "connection",
					"height": 50,
					"width": 90,
					"shape": "rounded",
					"label": "CFG",
					"type": "button",
					"left": 1040,
					"sends": [
						"/SCMD?printConfig"
					]
				},
				{
					"requiresSendReponse": false,
					"top": 590,
					"connection": "connection",
					"height": 50,
					"width": 90,
					"shape": "rounded",
					"label": "OPT 2",
					"type": "button",
					"left": 1040
				},
				{
					"requiresSendReponse": false,
					"top": 470,
					"connection": "connection",
					"height": 50,
					"width": 90,
					"shape": "rounded",
					"label": "AUTOTUNE",
					"type": "button",
					"left": 1170,
					"border": "0,0,0",
					"sends": [
						"/SCMD?AUTOTUNE=1"
					]
				},
				{
					"offSend": "/VIFE?cameraOFF.sh",
					"requiresSendReponse": true,
					"top": 260,
					"onSend": "/VIFE?cameraON.sh",
					"offColor": "0,76,190",
					"width": 150,
					"height": 40,
					"type": "switch",
					"left": 140
				},
				{
					"text": "Video",
					"top": 260,
					"height": 40,
					"width": 110,
					"type": "label",
					"left": 20
				},
				{
					"top": 80,
					"left": 960,
					"width": 300,
					"height": 300,
					"type": "webview",
					"url": "http://192.168.1.145:54321/vj",
					"scrollable": false,
					"reloadButton": true
				},
				{
					"top": 460,
					"left": 370,
					"width": 260,
					"height": 260,
					"type": "webview",
					"url": "http://192.168.1.145:54321/ypr",
					"reloadButton": true,
					"scrollable": false
				},
				{
					"requiresSendReponse": false,
					"top": 530,
					"connection": "connection",
					"height": 50,
					"width": 90,
					"shape": "rounded",
					"label": "OPT3",
					"type": "button",
					"left": 1170
				}
			],
			"label": "RPi IO",
			"height": 800,
			"width": 1280,
			"connection": "connection",
			"fitToScreen": true
		},
		{
			"name": "empty",
			"label": "new",
			"connection": "connection",
			"sound": "active",
			"items": [
				{
					"top": 20,
					"left": 20,
					"width": 400,
					"height": 360,
					"type": "webview",
					"url": "http://192.168.1.145:54321/ypr"
				}
			],
			"fitToScreen": true,
			"width": 1280,
			"height": 800,
			"textcolor": "230,230,230",
			"background": "40,40,40"
		}
	],
	"switchOnSwipe": true,
	"orientation": "landscape"
}